<?xml version="1.0" encoding="utf-8"?>
<FrameLayout xmlns:android="http://schemas.android.com/apk/res/android"
    xmlns:app="http://schemas.android.com/apk/res-auto"
    android:id="@+id/sleep_custom_root"
    android:layout_width="match_parent" android:layout_height="match_parent"
    android:background="#80000000"
    android:clickable="true"
    android:focusable="true">

    <com.google.android.material.card.MaterialCardView
        android:layout_width="match_parent" android:layout_height="wrap_content"
        android:layout_marginHorizontal="24dp"
        android:layout_gravity="center"
        app:cardCornerRadius="24dp"
        app:cardElevation="8dp"
        app:cardBackgroundColor="#33000000"
        app:strokeColor="#30FFFFFF"
        app:strokeWidth="0.5dp">

        <LinearLayout android:layout_width="match_parent" android:layout_height="wrap_content"
            android:orientation="vertical" android:padding="20dp">

            <TextView android:layout_width="wrap_content" android:layout_height="wrap_content"
                android:text="自定义时间" android:textColor="#DDFFFFFF"
                android:textSize="18sp" android:fontFamily="sans-serif-medium"
                android:layout_marginBottom="16dp" android:layout_marginStart="4dp" />

            <LinearLayout android:layout_width="match_parent" android:layout_height="wrap_content"
                android:orientation="horizontal" android:gravity="center"
                android:layout_marginBottom="20dp">

                <EditText android:id="@+id/sleep_custom_input"
                    android:layout_width="80dp" android:layout_height="48dp"
                    android:text="30" android:gravity="center"
                    android:textColor="#FFFFFF" android:textSize="28sp"
                    android:fontFamily="sans-serif-medium"
                    android:inputType="number"
                    android:importantForAutofill="no"
                    android:background="@null" />

                <TextView android:layout_width="wrap_content" android:layout_height="wrap_content"
                    android:text=" 分钟" android:textColor="#B0FFFFFF"
                    android:textSize="16sp" />
            </LinearLayout>

            <LinearLayout android:layout_width="match_parent" android:layout_height="wrap_content"
                android:orientation="horizontal" android:gravity="center">

                <TextView android:id="@+id/sleep_custom_cancel" android:layout_width="0dp"
                    android:layout_height="40dp" android:layout_weight="1"
                    android:text="取消" android:gravity="center"
                    android:textColor="#99FFFFFF" android:textSize="15sp"
                    android:background="?attr/selectableItemBackground"
                    android:layout_marginEnd="8dp" />
                <TextView android:id="@+id/sleep_custom_confirm" android:layout_width="0dp"
                    android:layout_height="40dp" android:layout_weight="1"
                    android:text="确定" android:gravity="center"
                    android:textColor="#FFFFFF" android:textSize="15sp"
                    android:fontFamily="sans-serif-medium"
                    android:background="?attr/selectableItemBackground"
                    android:layout_marginStart="8dp" />
            </LinearLayout>
        </LinearLayout>
    </com.google.android.material.card.MaterialCardView>
</FrameLayout>
